{
"type": "FeatureCollection",
"name": "akiba",
"crs": { "type": "name", "properties": { "name": "urn:ogc:def:crs:OGC:1.3:CRS84" } },
"features": [
{ "type": "Feature", "properties": { "name": "秋葉原駅" }, "geometry": { "type": "Point", "coordinates": [ 139.773078918457088, 35.698401869505425 ] } }
]
}
